LICENSE
MANIFEST.in
README.md
setup.cfg
setup.py
airypi_rpi/__init__.py
airypi_rpi/auth.py
airypi_rpi/client.py
airypi_rpi/commandline.py
airypi_rpi/execute.py
airypi_rpi/smbus.so
airypi_rpi/spidev.so
airypi_rpi.egg-info/PKG-INFO
airypi_rpi.egg-info/SOURCES.txt
airypi_rpi.egg-info/dependency_links.txt
airypi_rpi.egg-info/entry_points.txt
airypi_rpi.egg-info/requires.txt
airypi_rpi.egg-info/top_level.txt
airypi_rpi/socketio_client/__init__.py
airypi_rpi/socketio_client/exceptions.py
airypi_rpi/socketio_client/tests.py
airypi_rpi/socketio_client/transports.py
airypi_rpi/websocket/__init__.py
airypi_rpi/websocket/_abnf.py
airypi_rpi/websocket/_app.py
airypi_rpi/websocket/_core.py
airypi_rpi/websocket/_exceptions.py
airypi_rpi/websocket/_utils.py
airypi_rpi/websocket/cacert.pem