Metadata-Version: 1.1
Name: airypi-rpi
Version: 0.0.1
Summary: The airypi client for Raspberry Pi
Home-page: https://www.airypi.com/docs/
Author: airypi
Author-email: dev@airypi.com
License: GPL v3
Keywords: raspberry,pi,client,server,cloud,library,airypi,control,io,gpio,serial,smbus,spi,i2c
Platform: UNKNOWN
Classifier: Development Status :: 4 - Beta
Classifier: Topic :: Software Development :: Libraries :: Python Modules
Classifier: Programming Language :: Python :: 2.7
Classifier: License :: OSI Approved :: GNU General Public License v3 or later (GPLv3+)
